assert_info/__init__.py
assert_info/__main__.py
assert_info/assert_token.py
assert_info/assertions.py
assert_info-0.2.1.dist-info/entry_points.txt
assert_info-0.2.1.dist-info/WHEEL
assert_info-0.2.1.dist-info/METADATA
assert_info-0.2.1.dist-info/RECORD
