Metadata-Version: 2.1
Name: assert-info
Version: 0.2.1
Summary: A tool for fixing bare assert statements
Home-page: https://gitlab.com/broster/assert-info
Author: Samuel Broster
Author-email: s.h.broster+gitlab@pm.me
Requires-Python: >=2.7, !=3.0.*, !=3.1.*, !=3.2.*, !=3.3.*, !=3.4.*, !=3.5.*
Classifier: Programming Language :: Python :: 2
Classifier: Programming Language :: Python :: 2.7
Classifier: Programming Language :: Python :: 3
Classifier: Programming Language :: Python :: 3.6
Classifier: Programming Language :: Python :: 3.7
Classifier: Programming Language :: Python :: 3.8
Requires-Dist: asttokens (>=2.0.4,<3.0.0)
Requires-Dist: docopt (>=0.6.2,<0.7.0)
Requires-Dist: six (>=1.14.0,<2.0.0)
Project-URL: Documentation, https://gitlab.com/broster/assert-info
Project-URL: Repository, https://gitlab.com/broster/assert-info
